26.11-Sram/senseamplifier.v
`timescale 1ns / 1ps

module mc
	 (
		inout bl,
		inout blb,
		input sw
	);

	reg bl_reg, blb_reg;

	initial bl_reg = 1'b1;

	always
	begin
		#1
		if(sw)
		begin
			bl_reg = bl;
			blb_reg = blb;
		end
		else
		begin
			blb_reg = ~bl_reg;
			bl_reg = ~blb_reg;
		end
	end

	assign bl = bl_reg;
	assign blb = blb_reg;

endmodule

module mc_tb;

	wire bl;
	wire blb;

	wire cl;
	wire clb;

	wire dl;
	wire dlb;

	reg drive_bl;
	reg drive_blb;
	reg sw;

	assign bl = sw ?
							((drive_bl == 1'bz)? cl: drive_bl):
							1'bz;

	assign blb = sw ?
							((drive_blb == 1'bz)? clb: drive_blb):
							1'bz;

	initial
	begin
		$dumpfile("dump.vcd");
		$dumpvars();

		//write 0
		#100 drive_bl=0;
		drive_blb=1;
		#1 sw=1;

		#100 sw=0;

		//read
		#100 drive_bl=1'bz;
		drive_blb=1'bz;
		#1 sw=1;

		//write 1
		#100 drive_bl=1;
		drive_blb=0;
		#1 sw=1;

		#100 sw=0;

		//read
		#100 drive_bl=1'bz;
		drive_blb=1'bz;
		#1 sw=1;

		#100 sw=0;

		#100 $finish;
	end

	mc mc0
	(
		.bl(cl),
		.blb(clb),
		.sw(sw)
	);

	endmodule

26.11-Sram/dump.vcd
$date
	Tue Nov 26 22:14:52 2019
$end
$version
	Icarus Verilog
$end
$timescale
	1ps
$end
$scope module mc_tb $end
$var wire 1 ! clb $end
$var wire 1 " cl $end
$var wire 1 # blb $end
$var wire 1 $ bl $end
$var reg 1 % drive_bl $end
$var reg 1 & drive_blb $end
$var reg 1 ' sw $end
$scope module mc0 $end
$var wire 1 ' sw $end
$var wire 1 ! blb $end
$var wire 1 " bl $end
$var reg 1 " bl_reg $end
$var reg 1 ! blb_reg $end
$upscope $end
$upscope $end
$enddefinitions $end
#0
$dumpvars
x'
x&
x%
x$
x#
1"
x!
$end
#1000
0!
#100000
1&
0%
#101000
1'
#201000
z$
z#
0'
#301000
z&
z%
#302000
x$
x#
1'
#402000
0#
1$
0&
1%
#503000
z$
z#
0'
#603000
z&
z%
#604000
x$
x#
1'
#704000
z$
z#
0'
