24.10-divisores/division.v
`timescale 1ns / 1ps

module division (
                     input         clk,
                     input         rst,
                     
                     input [3:0]   D, 
                     input [3:0]   d,
		     output [3:0]  q,
                     output [3:0]  r,
                     input         start,
                     output        done
                     );

   reg [3:0] counter;
   reg [3:0] divisor;
   reg [7:0] dividendo;
   reg 	     quociente;
   reg [3:0] resultado;



   assign q = dividendo [3:0];
   assign r = dividendo [7:4];

   assign done = (counter == 4'd4);

   always@(posedge clk)
     if(rst)
       counter <= 4'd4;
     else if (start)
       counter <= 4'd0;
     else if (counter != 4'd4)
       counter <= counter + 1'b1;
   
     always@(posedge clk)
	divisor <= d;

     always@(posedge clk)
	if(rst)
		dividendo <= 8'd0;
	else if (start)
		dividendo <= {4'd0,D[3:0]};
	else if (counter != 4'd4)
		dividendo <= {{resultado [3:0],dividendo[2:0]},quociente};

     always@*
	if (divisor<=dividendo[6:3]) begin
		quociente <= 1'd1;
		resultado <= dividendo[6:3] - divisor;
	end
	else begin
		quociente <= 1'd0;
		resultado <= dividendo[6:3];
	end

endmodule


module division_tb ();

   reg clk, rst;
   reg [3:0] D, d;
   wire [3:0] q,r;
   reg         start;
   wire        done;
   
   division div (
                       .clk(clk),
                       .rst(rst),
                     
                       .D(D), 
                       .d(d),
		       .q(q), 
                       .r(r),
                       .start(start),
                       .done(done)
                     );   

   initial begin

      $dumpfile("dump.vcd");
      $dumpvars;
      
      rst = 1;
      clk = 1;
      start = 0;

      D= 4'h4;
      d= 4'h4;

      @(posedge clk) #1 rst=0;

      #5 @(posedge clk) #1 start=1;
      @(posedge clk) #1 start=0;

      @(posedge done) $display("%d", q);
      
      @(posedge clk) $finish;
   end
   
   always #10 clk = ~clk;
 
endmodule

24.10-divisores/dump.vcd
$date
	Tue Oct 29 17:46:03 2019
$end
$version
	Icarus Verilog
$end
$timescale
	1ps
$end
$scope module division_tb $end
$var wire 4 ! r [3:0] $end
$var wire 4 " q [3:0] $end
$var wire 1 # done $end
$var reg 4 $ D [3:0] $end
$var reg 1 % clk $end
$var reg 4 & d [3:0] $end
$var reg 1 ' rst $end
$var reg 1 ( start $end
$scope module div $end
$var wire 4 ) D [3:0] $end
$var wire 1 % clk $end
$var wire 4 * d [3:0] $end
$var wire 1 ' rst $end
$var wire 1 ( start $end
$var wire 4 + r [3:0] $end
$var wire 4 , q [3:0] $end
$var wire 1 # done $end
$var reg 4 - counter [3:0] $end
$var reg 8 . dividendo [7:0] $end
$var reg 4 / divisor [3:0] $end
$var reg 1 0 quociente $end
$var reg 4 1 resultado [3:0] $end
$upscope $end
$upscope $end
$enddefinitions $end
#0
$dumpvars
b0 1
00
b100 /
b0 .
b100 -
b0 ,
b0 +
b100 *
b100 )
0(
1'
b100 &
1%
b100 $
1#
b0 "
b0 !
$end
#10000
0%
#20000
1%
#21000
0'
#30000
0%
#40000
1%
#41000
1(
#50000
0%
#60000
b100 "
b100 ,
b100 .
0#
b0 -
1%
#61000
0(
#70000
0%
#80000
b1 1
b1000 "
b1000 ,
b1 -
b1000 .
1%
#90000
0%
#100000
b10 1
b0 "
b0 ,
b1 !
b1 +
b10000 .
b10 -
1%
#110000
0%
#120000
b0 1
10
b10 !
b10 +
b11 -
b100000 .
1%
#130000
0%
#140000
00
b1 "
b1 ,
b0 !
b0 +
b1 .
1#
b100 -
1%
