17.10-multiplier/halfadder.v
`timescale 1ns / 1ps
module halfadder

	(
	        input a,
		input b,
		output cout,
                output s
	);
	
	assign s = a ^ b;
	assign cout = a & b;

endmodule

17.10-multiplier/top.v
`timescale 1ns / 1ps

module top 

	(
		input [1:0] a,
		input [1:0] b,
		output [3:0] s
	);

	wire [1:0] ab0;
	wire [1:0] ab1;
	wire carry;

	assign ab0[0] = a[0] & b[0];
	assign ab0[1] = a[1] & b[0];
	assign ab1[0] = a[0] & b[1];
	assign ab1[1] = a[1] & b[1];
	assign s[0] = ab0[0];

	halfadder ha1
	(
		.a(ab0[1]),
		.b(ab1[0]),
		.cout(carry),
                .s(s[1])
	);

	halfadder ha2
	(
		.a(ab1[1]),
		.b(carry),
		.cout(s[3]),
                .s(s[2])
	);
	
endmodule

17.10-multiplier/mult_tb.v
`timescale 1ns / 1ps

module carrylookahead_tb;
   
	parameter T = 25;

	reg [1:0] a;
	reg [1:0] b;
	wire [3:0] s;
   
   // Instantiate the Unit Under Test (UUT)
   top uut(
		.a(a),
		.b(b),
		.s(s)
	     );

	always
   		#(T) a[0] = ~a[0];
	always
   		#(2*T) a[1] = ~a[1];
	always
   		#(4*T) b[0] = ~b[0];
	always
   		#(8*T) b[1] = ~b[1];
	
   initial begin
	
	
	$dumpfile("multcomb.vcd");
	$dumpvars();        

	// Initialize Inputs
	a = 0;
	b = 0; 

	#(17*T)
	$finish;

   end // initial begin

endmodule

17.10-multiplier/multcomb.vcd
$date
	Thu Oct 17 17:01:56 2019
$end
$version
	Icarus Verilog
$end
$timescale
	1ps
$end
$scope module carrylookahead_tb $end
$var wire 4 ! s [3:0] $end
$var reg 2 " a [1:0] $end
$var reg 2 # b [1:0] $end
$scope module uut $end
$var wire 2 $ a [1:0] $end
$var wire 2 % b [1:0] $end
$var wire 4 & s [3:0] $end
$var wire 1 ' carry $end
$var wire 2 ( ab1 [1:0] $end
$var wire 2 ) ab0 [1:0] $end
$scope module ha1 $end
$var wire 1 * a $end
$var wire 1 + b $end
$var wire 1 ' cout $end
$var wire 1 , s $end
$upscope $end
$scope module ha2 $end
$var wire 1 - a $end
$var wire 1 ' b $end
$var wire 1 . cout $end
$var wire 1 / s $end
$upscope $end
$upscope $end
$upscope $end
$enddefinitions $end
#0
$dumpvars
0/
0.
0-
0,
0+
0*
b0 )
b0 (
0'
b0 &
b0 %
b0 $
b0 #
b0 "
b0 !
$end
#25000
b1 "
b1 $
#50000
b10 "
b10 $
#75000
b11 "
b11 $
#100000
b0 "
b0 $
b1 #
b1 %
#125000
b1 !
b1 &
b1 )
b1 "
b1 $
#150000
1,
b10 !
b10 &
1*
b10 )
b10 "
b10 $
#175000
b11 !
b11 &
b11 )
b11 "
b11 $
#200000
0,
b0 !
b0 &
0*
b0 )
b0 "
b0 $
b10 #
b10 %
#225000
b10 !
b10 &
1,
1+
b1 (
b1 "
b1 $
#250000
0,
b100 !
b100 &
1/
0+
1-
b10 (
b10 "
b10 $
#275000
b110 !
b110 &
1,
1+
b11 (
b11 "
b11 $
#300000
0,
b0 !
b0 &
0/
0+
0-
b0 (
b0 "
b0 $
b11 #
b11 %
#325000
1,
b11 !
b11 &
1+
b1 )
b1 (
b1 "
b1 $
#350000
1/
b110 !
b110 &
0+
1*
1-
b10 )
b10 (
b10 "
b10 $
#375000
0/
1.
0,
1'
b1001 !
b1001 &
1+
b11 )
b11 (
b11 "
b11 $
#400000
0'
0/
0.
b0 !
b0 &
0*
0+
0-
b0 )
b0 (
b0 "
b0 $
b0 #
b0 %
#425000
b1 "
b1 $
