22.10-multipliersigned/add_shft_mul.v
`timescale 1ns / 1ps

module add_shft_mul (
                     input         clk,
                     input         rst,
                     
                     input signed [7:0]   a, 
                     input signed [7:0]   b,
                     output reg signed [15:0] c,
                     input         start,
                     output        done
                     );

   reg [3:0]                     counter;


   assign done = (counter == 4'd8);

   always@(posedge clk)
     if(rst)
       counter <= 4'd8;
     else if (start)
       counter <= 4'd0;
     else if (counter != 4'd8)
       counter <= counter + 1'b1;
   
   
     always@(posedge clk)
     if(rst)
       c <= 16'd0;
     else if(counter != 4'd8) begin
	if (counter == 4'd7 && b[counter]==1)
		c <= {c[15],c[15:1]} - {{a[7],a[7:0]},7'b0};
	else
        	c <= {c[15],c[15:1]} + (b[counter]? {{a[7],a[7:0]},7'b0}: 16'd0); //se for dif 0 a<<7 se ==0 16'd0
     end
endmodule


module add_shft_mul_tb ();

   reg clk, rst;
   reg [7:0] a, b;
   wire [15:0] c;
   reg         start;
   wire        done;
   
   add_shft_mul mult0 (
                       .clk(clk),
                       .rst(rst),
                     
                       .a(a), 
                       .b(b),
                       .c(c),
                       .start(start),
                       .done(done)
                     );   

   initial begin

      $dumpfile("dump.vcd");
      $dumpvars;
      
      rst = 1;
      clk = 1;
      start = 0;

      b= 8'h64;
      a = 8'hbf;

      @(posedge clk) #1 rst=0;

      #5 @(posedge clk) #1 start=1;
      @(posedge clk) #1 start=0;

      @(posedge done) $display("%d", c);
      
      @(posedge clk) $finish;
   end
   
   always #10 clk = ~clk;
 
endmodule

22.10-multipliersigned/dump.vcd
$date
	Tue Oct 22 21:14:16 2019
$end
$version
	Icarus Verilog
$end
$timescale
	1ps
$end
$scope module add_shft_mul_tb $end
$var wire 1 ! done $end
$var wire 16 " c [15:0] $end
$var reg 8 # a [7:0] $end
$var reg 8 $ b [7:0] $end
$var reg 1 % clk $end
$var reg 1 & rst $end
$var reg 1 ' start $end
$scope module mult0 $end
$var wire 8 ( a [7:0] $end
$var wire 8 ) b [7:0] $end
$var wire 1 % clk $end
$var wire 1 & rst $end
$var wire 1 ' start $end
$var wire 1 ! done $end
$var reg 16 * c [15:0] $end
$var reg 4 + counter [3:0] $end
$upscope $end
$upscope $end
$enddefinitions $end
#0
$dumpvars
b1000 +
b0 *
b1100100 )
b10111111 (
0'
1&
1%
b1100100 $
b10111111 #
b0 "
1!
$end
#10000
0%
#20000
1%
#21000
0&
#30000
0%
#40000
1%
#41000
1'
#50000
0%
#60000
0!
b0 +
1%
#61000
0'
#70000
0%
#80000
b1 +
1%
#90000
0%
#100000
b10 +
1%
#110000
0%
#120000
b11 +
b1101111110000000 "
b1101111110000000 *
1%
#130000
0%
#140000
b1110111111000000 "
b1110111111000000 *
b100 +
1%
#150000
0%
#160000
b101 +
b1111011111100000 "
b1111011111100000 *
1%
#170000
0%
#180000
b1101101101110000 "
b1101101101110000 *
b110 +
1%
#190000
0%
#200000
b111 +
b1100110100111000 "
b1100110100111000 *
1%
#210000
0%
#220000
b1110011010011100 "
b1110011010011100 *
1!
b1000 +
1%
