29.10-Booth/booth.v
`timescale 1ns / 1ps

module booth (
                     input         clk,
                     input         rst,

                     input [31:0]   M,
                     input [31:0]   m,
                     output [63:0] result,
		                 output reg done
                     );

	reg [64:0]		prodmultreg;
	reg			pc;
	reg [5:0]			counter;

	assign result = prodmultreg [64:1];

	always@(posedge clk)
	if(rst) begin
		prodmultreg <= 65'b0;
		pc<=0;
		counter<=0;
		done<=0;
    end
	else begin
		case (pc)
			0 : begin
        prodmultreg[32:1] <= m;
      end
			1 : begin
        if(done==0) begin
				case (prodmultreg[1:0])
					2'b01: begin
						prodmultreg <= $signed ({prodmultreg[64:33] + M,prodmultreg[32:0]})>>>1;
					end
					2'b10: begin
						prodmultreg <= $signed ({prodmultreg[64:33] - M,prodmultreg[32:0]})>>>1;
					end
					default: begin
						prodmultreg[63:0] <= prodmultreg[64:1];
            prodmultreg[64] <= prodmultreg[64];
					end
				endcase
        end
      end
      endcase
    if (counter == 0) begin
      pc <= pc + 1'b1;
      counter<=counter+1;
    end
    else if (counter != 6'd32) begin
			pc<=pc;
      counter<=counter+1;
    end
    else if (counter == 32) begin
			pc<=pc;
			done<=1;
			counter<=counter;
		end
	end
endmodule

module booth_tb ();

   reg clk;
   reg rst;
   reg [31:0] M;
   reg [31:0] m;
   wire [63:0] result;
   wire        done;

   booth mult0 (
                       .clk(clk),
                       .rst(rst),

                       .M(M),
                       .m(m),
                       .result(result),
                       .done(done)
                     );

   initial begin

      $dumpfile("booth.vcd");
      $dumpvars;

      rst = 1;
      clk = 1;

      M= 32'h7;
      m= 32'h8;

      @(posedge clk) #1 rst=0;

      @(posedge done) $display("%d", result);

      @(posedge clk) $finish;
   end

   always #10 clk = ~clk;

endmodule

29.10-Booth/booth.vcd
$date
	Tue Oct 29 21:56:28 2019
$end
$version
	Icarus Verilog
$end
$timescale
	1ps
$end
$scope module booth_tb $end
$var wire 64 ! result [63:0] $end
$var wire 1 " done $end
$var reg 32 # M [31:0] $end
$var reg 1 $ clk $end
$var reg 32 % m [31:0] $end
$var reg 1 & rst $end
$scope module mult0 $end
$var wire 32 ' M [31:0] $end
$var wire 1 $ clk $end
$var wire 32 ( m [31:0] $end
$var wire 1 & rst $end
$var wire 64 ) result [63:0] $end
$var reg 6 * counter [5:0] $end
$var reg 1 " done $end
$var reg 1 + pc $end
$var reg 65 , prodmultreg [64:0] $end
$upscope $end
$upscope $end
$enddefinitions $end
#0
$dumpvars
b0 ,
0+
b0 *
b0 )
b1000 (
b111 '
1&
b1000 %
1$
b111 #
0"
b0 !
$end
#10000
0$
#20000
1$
#21000
0&
#30000
0$
#40000
b1000 !
b1000 )
b1 *
1+
b10000 ,
1$
#50000
0$
#60000
b100 !
b100 )
b10 *
b1000 ,
1$
#70000
0$
#80000
b10 !
b10 )
b11 *
b100 ,
1$
#90000
0$
#100000
b1 !
b1 )
b100 *
b10 ,
1$
#110000
0$
#120000
b1111111111111111111111111111110010000000000000000000000000000000 !
b1111111111111111111111111111110010000000000000000000000000000000 )
b101 *
b11111111111111111111111111111100100000000000000000000000000000001 ,
1$
#130000
0$
#140000
b111000000000000000000000000000000 !
b111000000000000000000000000000000 )
b110 *
b1110000000000000000000000000000000 ,
1$
#150000
0$
#160000
b11100000000000000000000000000000 !
b11100000000000000000000000000000 )
b111 *
b111000000000000000000000000000000 ,
1$
#170000
0$
#180000
b1110000000000000000000000000000 !
b1110000000000000000000000000000 )
b1000 *
b11100000000000000000000000000000 ,
1$
#190000
0$
#200000
b111000000000000000000000000000 !
b111000000000000000000000000000 )
b1001 *
b1110000000000000000000000000000 ,
1$
#210000
0$
#220000
b11100000000000000000000000000 !
b11100000000000000000000000000 )
b1010 *
b111000000000000000000000000000 ,
1$
#230000
0$
#240000
b1110000000000000000000000000 !
b1110000000000000000000000000 )
b1011 *
b11100000000000000000000000000 ,
1$
#250000
0$
#260000
b111000000000000000000000000 !
b111000000000000000000000000 )
b1100 *
b1110000000000000000000000000 ,
1$
#270000
0$
#280000
b11100000000000000000000000 !
b11100000000000000000000000 )
b1101 *
b111000000000000000000000000 ,
1$
#290000
0$
#300000
b1110000000000000000000000 !
b1110000000000000000000000 )
b1110 *
b11100000000000000000000000 ,
1$
#310000
0$
#320000
b111000000000000000000000 !
b111000000000000000000000 )
b1111 *
b1110000000000000000000000 ,
1$
#330000
0$
#340000
b11100000000000000000000 !
b11100000000000000000000 )
b10000 *
b111000000000000000000000 ,
1$
#350000
0$
#360000
b1110000000000000000000 !
b1110000000000000000000 )
b10001 *
b11100000000000000000000 ,
1$
#370000
0$
#380000
b111000000000000000000 !
b111000000000000000000 )
b10010 *
b1110000000000000000000 ,
1$
#390000
0$
#400000
b11100000000000000000 !
b11100000000000000000 )
b10011 *
b111000000000000000000 ,
1$
#410000
0$
#420000
b1110000000000000000 !
b1110000000000000000 )
b10100 *
b11100000000000000000 ,
1$
#430000
0$
#440000
b111000000000000000 !
b111000000000000000 )
b10101 *
b1110000000000000000 ,
1$
#450000
0$
#460000
b11100000000000000 !
b11100000000000000 )
b10110 *
b111000000000000000 ,
1$
#470000
0$
#480000
b1110000000000000 !
b1110000000000000 )
b10111 *
b11100000000000000 ,
1$
#490000
0$
#500000
b111000000000000 !
b111000000000000 )
b11000 *
b1110000000000000 ,
1$
#510000
0$
#520000
b11100000000000 !
b11100000000000 )
b11001 *
b111000000000000 ,
1$
#530000
0$
#540000
b1110000000000 !
b1110000000000 )
b11010 *
b11100000000000 ,
1$
#550000
0$
#560000
b111000000000 !
b111000000000 )
b11011 *
b1110000000000 ,
1$
#570000
0$
#580000
b11100000000 !
b11100000000 )
b11100 *
b111000000000 ,
1$
#590000
0$
#600000
b1110000000 !
b1110000000 )
b11101 *
b11100000000 ,
1$
#610000
0$
#620000
b111000000 !
b111000000 )
b11110 *
b1110000000 ,
1$
#630000
0$
#640000
b11100000 !
b11100000 )
b11111 *
b111000000 ,
1$
#650000
0$
#660000
b1110000 !
b1110000 )
b100000 *
b11100000 ,
1$
#670000
0$
#680000
b111000 !
b111000 )
1"
b1110000 ,
1$
