5.11-memory/fibonnacci.v
`timescale 1ns / 1ps

module fibonnacci (
                     input [3:0]   a,
                     output [5:0]   number

                     );

	reg [5:0] memrom[0:9];

	initial
	begin
	$readmemb ("program.hex",memrom,0,9);
	end

	assign number=memrom[a];

endmodule

module fibonnacci_tb ();

  parameter T=10;

   reg [3:0] a;
   wire [5:0] number;


   fibonnacci sequence (
                       .a(a),
                       .number(number)
                     );

   initial begin

      $dumpfile("fibonnacci.vcd");
      $dumpvars;

      a= 4'b0;

      #(20*T)

      $finish;
   end
   always #10
    if(a!=9)
      a = a+1;
    else
      a = 0;

endmodule

5.11-memory/fibonnacci.vcd
$date
	Tue Nov  5 19:04:28 2019
$end
$version
	Icarus Verilog
$end
$timescale
	1ps
$end
$scope module fibonnacci_tb $end
$var wire 6 ! number [5:0] $end
$var reg 4 " a [3:0] $end
$scope module sequence $end
$var wire 4 # a [3:0] $end
$var wire 6 $ number [5:0] $end
$upscope $end
$upscope $end
$enddefinitions $end
#0
$dumpvars
b0 $
b0 #
b0 "
b0 !
$end
#10000
b1 !
b1 $
b1 "
b1 #
#20000
b10 "
b10 #
#30000
b10 !
b10 $
b11 "
b11 #
#40000
b11 !
b11 $
b100 "
b100 #
#50000
b101 !
b101 $
b101 "
b101 #
#60000
b1000 !
b1000 $
b110 "
b110 #
#70000
b1101 !
b1101 $
b111 "
b111 #
#80000
b10101 !
b10101 $
b1000 "
b1000 #
#90000
b100010 !
b100010 $
b1001 "
b1001 #
#100000
b0 !
b0 $
b0 "
b0 #
#110000
b1 !
b1 $
b1 "
b1 #
#120000
b10 "
b10 #
#130000
b10 !
b10 $
b11 "
b11 #
#140000
b11 !
b11 $
b100 "
b100 #
#150000
b101 !
b101 $
b101 "
b101 #
#160000
b1000 !
b1000 $
b110 "
b110 #
#170000
b1101 !
b1101 $
b111 "
b111 #
#180000
b10101 !
b10101 $
b1000 "
b1000 #
#190000
b100010 !
b100010 $
b1001 "
b1001 #
#200000
b0 !
b0 $
b0 "
b0 #
